sekuhsgehkuljsgehljkesglhku/__init__.py
sekuhsgehkuljsgehljkesglhku-1.0.0.dist-info/METADATA
sekuhsgehkuljsgehljkesglhku-1.0.0.dist-info/WHEEL
sekuhsgehkuljsgehljkesglhku-1.0.0.dist-info/top_level.txt
sekuhsgehkuljsgehljkesglhku-1.0.0.dist-info/RECORD
