Metadata-Version: 2.1
Name: sekuhsgehkuljsgehljkesglhku
Version: 1.0.0
Summary: kekw package
Home-page: UNKNOWN
Author: StarlessGem
Author-email: StarlessGem@gmail.com
License: UNKNOWN
Keywords: python
Platform: UNKNOWN
Classifier: Operating System :: Microsoft :: Windows
